mybox/__init__.py
mybox/cli.py
mybox/mybox.py
mybox_tool-0.1.0.dist-info/METADATA
mybox_tool-0.1.0.dist-info/WHEEL
mybox_tool-0.1.0.dist-info/entry_points.txt
mybox_tool-0.1.0.dist-info/top_level.txt
mybox_tool-0.1.0.dist-info/RECORD
