Metadata-Version: 2.1
Name: mybox-tool
Version: 0.1.0
Summary: A powerful multi-repository management tool for Git projects
Home-page: https://github.com/beliefgp/mybox
Author: belief
Author-email: belief.bian@gmail.com
Project-URL: Bug Tracker, https://github.com/beliefgp/mybox/issues
Project-URL: Documentation, https://github.com/beliefgp/mybox/tree/main/docs
Project-URL: Source Code, https://github.com/beliefgp/mybox
Keywords: git repository management tool workspace
Classifier: Development Status :: 4 - Beta
Classifier: Intended Audience :: Developers
Classifier: Topic :: Software Development :: Version Control :: Git
Classifier: Programming Language :: Python :: 3
Classifier: Programming Language :: Python :: 3.8
Classifier: Programming Language :: Python :: 3.9
Classifier: Programming Language :: Python :: 3.10
Classifier: Programming Language :: Python :: 3.11
Classifier: License :: OSI Approved :: MIT License
Classifier: Operating System :: OS Independent
Requires-Python: >=3.8
Requires-Dist: click>=8.0.0
Requires-Dist: pyyaml>=6.0.0
Requires-Dist: rich>=13.0.0
Requires-Dist: gitpython>=3.1.0
Provides-Extra: dev
Requires-Dist: pytest>=7.0.0; extra == "dev"
Requires-Dist: pytest-cov>=4.0.0; extra == "dev"
Requires-Dist: black>=22.0.0; extra == "dev"
Requires-Dist: isort>=5.0.0; extra == "dev"
Requires-Dist: flake8>=4.0.0; extra == "dev"
Requires-Dist: mypy>=1.0.0; extra == "dev"
